funckeeper/__init__.py
funckeeper/core.py
funckeeper-0.1.3.dist-info/LICENSE
funckeeper-0.1.3.dist-info/METADATA
funckeeper-0.1.3.dist-info/WHEEL
funckeeper-0.1.3.dist-info/RECORD
