Metadata-Version: 2.1
Name: funckeeper
Version: 0.1.3
Summary: A Python function execution recorder and tracker
Home-page: https://github.com/xiwen-haochi/funckeeper
License: MIT
Keywords: python,function,tracker,recorder,debugging
Author: 'fkl'
Author-email: 18654198191@163.com
Requires-Python: >=3.6
Classifier: Development Status :: 4 - Beta
Classifier: Intended Audience :: Developers
Classifier: License :: OSI Approved :: MIT License
Classifier: Programming Language :: Python :: 3
Classifier: Programming Language :: Python :: 3.6
Classifier: Programming Language :: Python :: 3.7
Classifier: Programming Language :: Python :: 3.8
Classifier: Programming Language :: Python :: 3.9
Classifier: Programming Language :: Python :: 3.10
Classifier: Programming Language :: Python :: 3.11
Classifier: Programming Language :: Python :: 3.12
Classifier: Programming Language :: Python :: 3.13
Classifier: Topic :: Software Development :: Debuggers
Classifier: Topic :: Software Development :: Libraries :: Python Modules
Project-URL: Repository, https://github.com/xiwen-haochi/funckeeper
